text/__init__.py
text/__main__.py
text/accent_typing_formatter.py
text/const.py
text/extract_human.py
text/preprocess.py
text/unicode_converter.py
text/utils.py
nlp_preprocessing_qvm9-0.0.4.dist-info/LICENSE
nlp_preprocessing_qvm9-0.0.4.dist-info/METADATA
nlp_preprocessing_qvm9-0.0.4.dist-info/WHEEL
nlp_preprocessing_qvm9-0.0.4.dist-info/entry_points.txt
nlp_preprocessing_qvm9-0.0.4.dist-info/top_level.txt
nlp_preprocessing_qvm9-0.0.4.dist-info/RECORD
