Metadata-Version: 2.1
Name: nlp-preprocessing-qvm9
Version: 0.0.4
Summary: Fix the import error
Author-email: quangvm9 <quangvm9@fpt.com.vn>
License: MIT License
Keywords: nlp,text,preprocessing
Classifier: License :: OSI Approved :: MIT License
Classifier: Programming Language :: Python
Classifier: Programming Language :: Python :: 3
Requires-Python: >=3.6
License-File: LICENSE
Requires-Dist: Unidecode
Requires-Dist: tqdm
Requires-Dist: pandas
Requires-Dist: numpy
Requires-Dist: regex
Provides-Extra: dev
Requires-Dist: black ; extra == 'dev'
Requires-Dist: bumpver ; extra == 'dev'
Requires-Dist: isort ; extra == 'dev'
Requires-Dist: pip-tools ; extra == 'dev'
Requires-Dist: pytest ; extra == 'dev'
